{
  "mcpServers": {
    "supabase": {
      "type": "stdio",
      "command": "npx",
      "args": [
        "-y",
        "@supabase/mcp-server-supabase"
      ],
      "env": {}
    },
    "playwright": {
      "type": "stdio",
      "command": "npx",
      "args": [
        "-y",
        "@playwright/mcp"
      ],
      "env": {}
    },
    "sequential-thinking": {
      "type": "stdio",
      "command": "npx",
      "args": [
        "-y",
        "@modelcontextprotocol/server-sequential-thinking"
      ],
      "env": {}
    },
    "context7": {
      "type": "stdio",
      "command": "npx",
      "args": [
        "-y",
        "@upstash/context7-mcp"
      ],
      "env": {}
    },
    "firebase": {
      "type": "stdio",
      "command": "npx",
      "args": [
        "-y",
        "@gannonh/firebase-mcp"
      ],
      "env": {
        "SERVICE_ACCOUNT_KEY_PATH": "C:\\Users\\JSS\\.firebase\\serviceAccountKey.json"
      }
    },
    "vercel": {
      "type": "http",
      "url": "https://mcp.vercel.com"
    }
  }
}